dupliganger/__init__.py
dupliganger/__main__.py
dupliganger/_version.py
dupliganger/annotate_qtrim.py
dupliganger/barcode_split_quality_filter_umi_anno.py
dupliganger/build_read_and_loc_dbs.py
dupliganger/command_line.py
dupliganger/common.py
dupliganger/constants.py
dupliganger/db.py
dupliganger/dedup.py
dupliganger/dupliganger.py
dupliganger/exceptions.py
dupliganger/qtrim.py
dupliganger/remove_adapter.py
dupliganger/remove_umi.py
dupliganger/sam.py
dupliganger-0.991.dist-info/LICENSE.txt
dupliganger-0.991.dist-info/METADATA
dupliganger-0.991.dist-info/WHEEL
dupliganger-0.991.dist-info/entry_points.txt
dupliganger-0.991.dist-info/top_level.txt
dupliganger-0.991.dist-info/zip-safe
dupliganger-0.991.dist-info/RECORD
