Metadata-Version: 2.1
Name: dupliganger
Version: 0.991
Summary: A reference-based, UMI-aware, 5ʹ-trimming-aware PCR duplicate removal pipeline.
Home-page: https://github.com/uoregon-postlethwait/dupliganger
Author: Postlethwait Lab, University of Oregon
Author-email: postlethwait.lab@gmail.com
License: LICENSE.txt
Project-URL: Source, https://github.com/uoregon-postlethwait/dupliganger
Project-URL: Bug Reports, https://github.com/uoregon-postlethwait/dupliganger/issues
Keywords: bioinformatics
Platform: UNKNOWN
Classifier: Development Status :: 5 - Production/Stable
Classifier: Intended Audience :: Science/Research
Classifier: Topic :: Scientific/Engineering :: Bio-Informatics
Classifier: License :: Free for non-commercial use
Classifier: Programming Language :: Python :: 2
Classifier: Programming Language :: Python :: 2.7
Classifier: Programming Language :: Python :: 3
Classifier: Programming Language :: Python :: 3.4
Classifier: Programming Language :: Python :: 3.5
Classifier: Programming Language :: Python :: 3.6
Classifier: Programming Language :: Python :: 3.7
Requires-Python: >=2.7, !=3.0.*, !=3.1.*, !=3.2.*, !=3.3.*, <4
Requires-Dist: docopt
Requires-Dist: lmdb
Requires-Dist: distance
Requires-Dist: future
Requires-Dist: psutil
